DaoProject/__init__.py
DaoProject/contents.py
DaoProject/graph.py
DaoProject/logging_utils.py
DaoProject/server.py
DaoProject/sql_utils.py
DaoProject/front_end/__init__.py
DaoProject/front_end/dao_cli.py
DaoProject/front_end/dao_web.py
DaoProject-1.0.0.dist-info/DESCRIPTION.rst
DaoProject-1.0.0.dist-info/METADATA
DaoProject-1.0.0.dist-info/RECORD
DaoProject-1.0.0.dist-info/WHEEL
DaoProject-1.0.0.dist-info/entry_points.txt
DaoProject-1.0.0.dist-info/metadata.json
DaoProject-1.0.0.dist-info/top_level.txt
