Metadata-Version: 2.0
Name: DaoProject
Version: 1.0.0
Summary: 描述信息
Home-page: UNKNOWN
Author: 江斌
License: UNKNOWN
Platform: UNKNOWN
Requires-Python: >=3.6
